{
  "AllIds": [
    10008,
    10009,
    10010,
    10011,
    10012,
    10013,
    10014,
    10015,
    10024,
    10025,
    10026,
    10027,
    10028,
    10029,
    10030,
    10031,
    10040,
    10041,
    10042,
    10043,
    10044,
    10045,
    10046
  ],
  "Data": {
    "10008": {
      "boosteffectid": [
        1900892,
        1900893,
        1900894,
        1900574
      ],
      "boosteffectpicid": [
        13014,
        13017,
        13018,
        13019
      ],
      "boostnameid": [
        1900901,
        1900902,
        1900903,
        1900570
      ],
      "id": 10008
    },
    "10009": {
      "boosteffectid": [
        1900892,
        1900893,
        1900895,
        1900574
      ],
      "boosteffectpicid": [
        13014,
        13017,
        13016,
        13019
      ],
      "boostnameid": [
        1900901,
        1900902,
        1900903,
        1900570
      ],
      "id": 10009
    },
    "10010": {
      "boosteffectid": [
        1900892,
        1900897,
        1900894,
        1900574
      ],
      "boosteffectpicid": [
        13014,
        13017,
        13018,
        13019
      ],
      "boostnameid": [
        1900901,
        1900902,
        1900903,
        1900570
      ],
      "id": 10010
    },
    "10011": {
      "boosteffectid": [
        1900896,
        1900893,
        1900899,
        1900574
      ],
      "boosteffectpicid": [
        13014,
        13017,
        13016,
        13019
      ],
      "boostnameid": [
        1900901,
        1900902,
        1900903,
        1900570
      ],
      "id": 10011
    },
    "10012": {
      "boosteffectid": [
        1900896,
        1900893,
        1900895,
        1900574
      ],
      "boosteffectpicid": [
        13014,
        13017,
        13018,
        13019
      ],
      "boostnameid": [
        1900901,
        1900902,
        1900903,
        1900570
      ],
      "id": 10012
    },
    "10013": {
      "boosteffectid": [
        1900896,
        1900897,
        1900898,
        1900574
      ],
      "boosteffectpicid": [
        13014,
        13017,
        13016,
        13019
      ],
      "boostnameid": [
        1900901,
        1900902,
        1900903,
        1900570
      ],
      "id": 10013
    },
    "10014": {
      "boosteffectid": [
        1900896,
        1900897,
        1900900,
        1900574
      ],
      "boosteffectpicid": [
        13014,
        13017,
        13016,
        13019
      ],
      "boostnameid": [
        1900901,
        1900902,
        1900903,
        1900570
      ],
      "id": 10014
    },
    "10015": {
      "boosteffectid": [
        1900896,
        1900897,
        1900900,
        1900905
      ],
      "boosteffectpicid": [
        13017,
        13018,
        13016,
        13019
      ],
      "boostnameid": [
        1900901,
        1900902,
        1900903,
        1900904
      ],
      "id": 10015
    },
    "10024": {
      "boosteffectid": [
        1900892,
        1900893,
        1900894,
        1900574
      ],
      "boosteffectpicid": [
        13014,
        13017,
        13018,
        13019
      ],
      "boostnameid": [
        1900901,
        1900902,
        1900903,
        1900570
      ],
      "id": 10024
    },
    "10025": {
      "boosteffectid": [
        1900892,
        1900893,
        1900895,
        1900574
      ],
      "boosteffectpicid": [
        13014,
        13017,
        13016,
        13019
      ],
      "boostnameid": [
        1900901,
        1900902,
        1900903,
        1900570
      ],
      "id": 10025
    },
    "10026": {
      "boosteffectid": [
        1900892,
        1900897,
        1900894,
        1900574
      ],
      "boosteffectpicid": [
        13014,
        13017,
        13018,
        13019
      ],
      "boostnameid": [
        1900901,
        1900902,
        1900903,
        1900570
      ],
      "id": 10026
    },
    "10027": {
      "boosteffectid": [
        1900896,
        1900893,
        1900899,
        1900574
      ],
      "boosteffectpicid": [
        13014,
        13017,
        13016,
        13019
      ],
      "boostnameid": [
        1900901,
        1900902,
        1900903,
        1900570
      ],
      "id": 10027
    },
    "10028": {
      "boosteffectid": [
        1900896,
        1900893,
        1900895,
        1900574
      ],
      "boosteffectpicid": [
        13014,
        13017,
        13018,
        13019
      ],
      "boostnameid": [
        1900901,
        1900902,
        1900903,
        1900570
      ],
      "id": 10028
    },
    "10029": {
      "boosteffectid": [
        1900896,
        1900897,
        1900898,
        1900574
      ],
      "boosteffectpicid": [
        13014,
        13017,
        13016,
        13019
      ],
      "boostnameid": [
        1900901,
        1900902,
        1900903,
        1900570
      ],
      "id": 10029
    },
    "10030": {
      "boosteffectid": [
        1900896,
        1900897,
        1900900,
        1900574
      ],
      "boosteffectpicid": [
        13014,
        13017,
        13016,
        13019
      ],
      "boostnameid": [
        1900901,
        1900902,
        1900903,
        1900570
      ],
      "id": 10030
    },
    "10031": {
      "boosteffectid": [
        1900896,
        1900897,
        1900900,
        1900905
      ],
      "boosteffectpicid": [
        13017,
        13018,
        13016,
        13019
      ],
      "boostnameid": [
        1900901,
        1900902,
        1900903,
        1900904
      ],
      "id": 10031
    },
    "10040": {
      "boosteffectid": [
        1900892,
        1900893,
        1900894,
        1900574
      ],
      "boosteffectpicid": [
        13014,
        13017,
        13018,
        13019
      ],
      "boostnameid": [
        1900901,
        1900902,
        1900903,
        1900570
      ],
      "id": 10040
    },
    "10041": {
      "boosteffectid": [
        1900892,
        1900893,
        1900895,
        1900574
      ],
      "boosteffectpicid": [
        13014,
        13017,
        13016,
        13019
      ],
      "boostnameid": [
        1900901,
        1900902,
        1900903,
        1900570
      ],
      "id": 10041
    },
    "10042": {
      "boosteffectid": [
        1900892,
        1900897,
        1900894,
        1900574
      ],
      "boosteffectpicid": [
        13014,
        13017,
        13018,
        13019
      ],
      "boostnameid": [
        1900901,
        1900902,
        1900903,
        1900570
      ],
      "id": 10042
    },
    "10043": {
      "boosteffectid": [
        1900896,
        1900893,
        1900899,
        1900574
      ],
      "boosteffectpicid": [
        13014,
        13017,
        13016,
        13019
      ],
      "boostnameid": [
        1900901,
        1900902,
        1900903,
        1900570
      ],
      "id": 10043
    },
    "10044": {
      "boosteffectid": [
        1900896,
        1900893,
        1900895,
        1900574
      ],
      "boosteffectpicid": [
        13014,
        13017,
        13018,
        13019
      ],
      "boostnameid": [
        1900901,
        1900902,
        1900903,
        1900570
      ],
      "id": 10044
    },
    "10045": {
      "boosteffectid": [
        1900896,
        1900897,
        1900898,
        1900574
      ],
      "boosteffectpicid": [
        13014,
        13017,
        13016,
        13019
      ],
      "boostnameid": [
        1900901,
        1900902,
        1900903,
        1900570
      ],
      "id": 10045
    },
    "10046": {
      "boosteffectid": [
        1900896,
        1900897,
        1900900,
        1900574
      ],
      "boosteffectpicid": [
        13014,
        13017,
        13016,
        13019
      ],
      "boostnameid": [
        1900901,
        1900902,
        1900903,
        1900570
      ],
      "id": 10046
    }
  }
}
