{
  "AllIds": [
    1001,
    2001,
    2002,
    2003,
    2004,
    2005,
    2006,
    2007,
    2008,
    3001,
    4001,
    4002,
    4003,
    4004,
    4005,
    4006,
    4007,
    4008,
    4009,
    4010,
    4011,
    4012,
    5001,
    6001,
    7001,
    7003,
    7004,
    7005,
    7006,
    7008,
    7009,
    7010,
    7012,
    7013,
    7014,
    7015,
    7016,
    8004,
    9001,
    10002,
    10003,
    10004,
    10005,
    10006,
    10007,
    10008,
    10009,
    10010,
    10011,
    10012,
    10013,
    10014,
    10015,
    10016,
    10017,
    10018,
    10019,
    11005,
    11006,
    11007,
    11008,
    12002,
    12003,
    13002,
    13003,
    13004,
    13005,
    13006,
    13007,
    13008,
    13009,
    13010,
    13011,
    13012,
    13013,
    13014,
    13015,
    13016,
    13017,
    13018,
    13019,
    15001,
    15002,
    15004,
    15005,
    15006,
    18001,
    19001,
    20001,
    21001,
    22001,
    23001,
    24001,
    25001,
    26001,
    27001,
    28001,
    29001,
    30001,
    31001,
    32001,
    33001,
    34001,
    35001,
    36001,
    37001,
    38001,
    39001,
    39002,
    39003,
    39004,
    39005,
    39006,
    39007,
    39008,
    39009,
    39010,
    39011,
    39012,
    39013,
    39014,
    39015,
    39016,
    40001,
    41001,
    42001,
    42002,
    43001,
    44001,
    45001,
    45002,
    46001,
    47001,
    48001,
    801003,
    802003,
    802004,
    803003,
    804003,
    804004
  ],
  "Data": {
    "10002": {
      "activityLineId": 10,
      "closeTime": "2022-01-25 03:59:59",
      "id": 10002,
      "onChannel": "",
      "openTime": "2022-01-18 04:00:00",
      "parameter": "",
      "scheduleLimit": 10025,
      "scheduleinterval": 43,
      "specialentry": -1
    },
    "10003": {
      "activityLineId": 10,
      "closeTime": "2022-02-08 03:59:59",
      "id": 10003,
      "onChannel": "",
      "openTime": "2022-02-01 04:00:00",
      "parameter": "",
      "scheduleLimit": 10025,
      "scheduleinterval": 43,
      "specialentry": -1
    },
    "10004": {
      "activityLineId": 10,
      "closeTime": "2022-03-08 03:59:59",
      "id": 10004,
      "onChannel": "",
      "openTime": "2022-03-01 04:00:00",
      "parameter": "",
      "scheduleLimit": 10025,
      "scheduleinterval": 43,
      "specialentry": -1
    },
    "10005": {
      "activityLineId": 10,
      "closeTime": "2022-04-05 03:59:59",
      "id": 10005,
      "onChannel": "",
      "openTime": "2022-03-29 04:00:00",
      "parameter": "",
      "scheduleLimit": 10025,
      "scheduleinterval": 43,
      "specialentry": -1
    },
    "10006": {
      "activityLineId": 10,
      "closeTime": "2022-05-03 03:59:59",
      "id": 10006,
      "onChannel": "",
      "openTime": "2022-04-26 04:00:00",
      "parameter": "",
      "scheduleLimit": 10025,
      "scheduleinterval": 43,
      "specialentry": -1
    },
    "10007": {
      "activityLineId": 10,
      "closeTime": "2022-05-31 03:59:59",
      "id": 10007,
      "onChannel": "",
      "openTime": "2022-05-24 04:00:00",
      "parameter": "",
      "scheduleLimit": 10025,
      "scheduleinterval": 43,
      "specialentry": -1
    },
    "10008": {
      "activityLineId": 10,
      "closeTime": "2022-06-28 03:59:59",
      "id": 10008,
      "onChannel": "",
      "openTime": "2022-06-21 04:00:00",
      "parameter": "",
      "scheduleLimit": 10025,
      "scheduleinterval": 43,
      "specialentry": -1
    },
    "10009": {
      "activityLineId": 10,
      "closeTime": "2022-07-26 03:59:59",
      "id": 10009,
      "onChannel": "",
      "openTime": "2022-07-19 04:00:00",
      "parameter": "",
      "scheduleLimit": 10025,
      "scheduleinterval": 43,
      "specialentry": -1
    },
    "1001": {
      "activityLineId": 1,
      "closeTime": "2019-11-11 18:00:00",
      "id": 1001,
      "onChannel": "",
      "openTime": "2019-10-07 12:00:00",
      "parameter": "",
      "scheduleLimit": 10002,
      "scheduleinterval": -1,
      "specialentry": -1
    },
    "10010": {
      "activityLineId": 10,
      "closeTime": "2022-08-23 03:59:59",
      "id": 10010,
      "onChannel": "",
      "openTime": "2022-08-16 04:00:00",
      "parameter": "",
      "scheduleLimit": 10025,
      "scheduleinterval": 43,
      "specialentry": -1
    },
    "10011": {
      "activityLineId": 10,
      "closeTime": "2022-09-20 03:59:59",
      "id": 10011,
      "onChannel": "",
      "openTime": "2022-09-13 04:00:00",
      "parameter": "",
      "scheduleLimit": 10025,
      "scheduleinterval": 43,
      "specialentry": -1
    },
    "10012": {
      "activityLineId": 10,
      "closeTime": "2022-10-18 03:59:59",
      "id": 10012,
      "onChannel": "",
      "openTime": "2022-10-11 04:00:00",
      "parameter": "",
      "scheduleLimit": 10025,
      "scheduleinterval": 43,
      "specialentry": -1
    },
    "10013": {
      "activityLineId": 10,
      "closeTime": "2022-11-15 03:59:59",
      "id": 10013,
      "onChannel": "",
      "openTime": "2022-11-08 04:00:00",
      "parameter": "",
      "scheduleLimit": 10025,
      "scheduleinterval": 43,
      "specialentry": -1
    },
    "10014": {
      "activityLineId": 10,
      "closeTime": "2022-12-13 03:59:59",
      "id": 10014,
      "onChannel": "",
      "openTime": "2022-12-06 04:00:00",
      "parameter": "",
      "scheduleLimit": 10025,
      "scheduleinterval": 43,
      "specialentry": -1
    },
    "10015": {
      "activityLineId": 10,
      "closeTime": "2023-01-10 03:59:59",
      "id": 10015,
      "onChannel": "",
      "openTime": "2023-01-03 04:00:00",
      "parameter": "",
      "scheduleLimit": 10025,
      "scheduleinterval": 43,
      "specialentry": -1
    },
    "10016": {
      "activityLineId": 10,
      "closeTime": "2023-02-07 03:59:59",
      "id": 10016,
      "onChannel": "",
      "openTime": "2023-01-31 04:00:00",
      "parameter": "",
      "scheduleLimit": 10025,
      "scheduleinterval": 43,
      "specialentry": -1
    },
    "10017": {
      "activityLineId": 10,
      "closeTime": "2023-03-07 03:59:59",
      "id": 10017,
      "onChannel": "",
      "openTime": "2023-02-28 04:00:00",
      "parameter": "",
      "scheduleLimit": 10025,
      "scheduleinterval": 43,
      "specialentry": -1
    },
    "10018": {
      "activityLineId": 10,
      "closeTime": "2023-04-04 03:59:59",
      "id": 10018,
      "onChannel": "",
      "openTime": "2023-03-28 04:00:00",
      "parameter": "",
      "scheduleLimit": 10025,
      "scheduleinterval": 43,
      "specialentry": -1
    },
    "10019": {
      "activityLineId": 10,
      "closeTime": "2023-05-02 03:59:59",
      "id": 10019,
      "onChannel": "",
      "openTime": "2023-04-25 04:00:00",
      "parameter": "",
      "scheduleLimit": 10025,
      "scheduleinterval": 43,
      "specialentry": -1
    },
    "11005": {
      "activityLineId": 11,
      "closeTime": "2022-03-22 03:59:59",
      "id": 11005,
      "onChannel": "",
      "openTime": "2022-03-08 04:00:00",
      "parameter": "29001",
      "scheduleLimit": 12025,
      "scheduleinterval": 17,
      "specialentry": -1
    },
    "11006": {
      "activityLineId": 11,
      "closeTime": "2022-03-22 03:59:59",
      "id": 11006,
      "onChannel": "",
      "openTime": "2022-03-15 04:00:00",
      "parameter": "29001",
      "scheduleLimit": 12025,
      "scheduleinterval": 17,
      "specialentry": -1
    },
    "11007": {
      "activityLineId": 11,
      "closeTime": "2022-09-13 03:59:59",
      "id": 11007,
      "onChannel": "",
      "openTime": "2022-08-30 04:00:00",
      "parameter": "40001",
      "scheduleLimit": 12025,
      "scheduleinterval": 17,
      "specialentry": -1
    },
    "11008": {
      "activityLineId": 11,
      "closeTime": "2022-11-22 03:59:59",
      "id": 11008,
      "onChannel": "",
      "openTime": "2022-11-08 04:00:00",
      "parameter": "40001",
      "scheduleLimit": 12025,
      "scheduleinterval": 17,
      "specialentry": -1
    },
    "12002": {
      "activityLineId": 12,
      "closeTime": "2022-04-29 03:59:59",
      "id": 12002,
      "onChannel": "",
      "openTime": "2022-04-15 04:00:00",
      "parameter": "",
      "scheduleLimit": 12004,
      "scheduleinterval": 6,
      "specialentry": -1
    },
    "12003": {
      "activityLineId": 12,
      "closeTime": "2023-04-25 03:59:59",
      "id": 12003,
      "onChannel": "",
      "openTime": "2023-04-11 03:00:00",
      "parameter": "",
      "scheduleLimit": 12004,
      "scheduleinterval": 6,
      "specialentry": -1
    },
    "13002": {
      "activityLineId": 13,
      "closeTime": "2022-02-01 03:59:59",
      "id": 13002,
      "onChannel": "",
      "openTime": "2022-01-18 04:00:00",
      "parameter": "",
      "scheduleLimit": 10025,
      "scheduleinterval": 43,
      "specialentry": -1
    },
    "13003": {
      "activityLineId": 13,
      "closeTime": "2022-02-15 03:59:59",
      "id": 13003,
      "onChannel": "",
      "openTime": "2022-02-01 04:00:00",
      "parameter": "",
      "scheduleLimit": 10025,
      "scheduleinterval": 43,
      "specialentry": -1
    },
    "13004": {
      "activityLineId": 13,
      "closeTime": "2022-03-15 03:59:59",
      "id": 13004,
      "onChannel": "",
      "openTime": "2022-03-01 04:00:00",
      "parameter": "",
      "scheduleLimit": 10025,
      "scheduleinterval": 43,
      "specialentry": -1
    },
    "13005": {
      "activityLineId": 13,
      "closeTime": "2022-04-12 03:59:59",
      "id": 13005,
      "onChannel": "",
      "openTime": "2022-03-29 04:00:00",
      "parameter": "",
      "scheduleLimit": 10025,
      "scheduleinterval": 43,
      "specialentry": -1
    },
    "13006": {
      "activityLineId": 13,
      "closeTime": "2022-05-10 03:59:59",
      "id": 13006,
      "onChannel": "",
      "openTime": "2022-04-26 04:00:00",
      "parameter": "",
      "scheduleLimit": 10025,
      "scheduleinterval": 43,
      "specialentry": -1
    },
    "13007": {
      "activityLineId": 13,
      "closeTime": "2022-06-07 03:59:59",
      "id": 13007,
      "onChannel": "",
      "openTime": "2022-05-24 04:00:00",
      "parameter": "",
      "scheduleLimit": 10025,
      "scheduleinterval": 43,
      "specialentry": -1
    },
    "13008": {
      "activityLineId": 13,
      "closeTime": "2022-07-05 03:59:59",
      "id": 13008,
      "onChannel": "",
      "openTime": "2022-06-21 04:00:00",
      "parameter": "",
      "scheduleLimit": 10025,
      "scheduleinterval": 43,
      "specialentry": -1
    },
    "13009": {
      "activityLineId": 13,
      "closeTime": "2022-08-02 03:59:59",
      "id": 13009,
      "onChannel": "",
      "openTime": "2022-07-19 04:00:00",
      "parameter": "",
      "scheduleLimit": 10025,
      "scheduleinterval": 43,
      "specialentry": -1
    },
    "13010": {
      "activityLineId": 13,
      "closeTime": "2022-08-30 03:59:59",
      "id": 13010,
      "onChannel": "",
      "openTime": "2022-08-16 04:00:00",
      "parameter": "",
      "scheduleLimit": 10025,
      "scheduleinterval": 43,
      "specialentry": -1
    },
    "13011": {
      "activityLineId": 13,
      "closeTime": "2022-09-27 03:59:59",
      "id": 13011,
      "onChannel": "",
      "openTime": "2022-09-13 04:00:00",
      "parameter": "",
      "scheduleLimit": 10025,
      "scheduleinterval": 43,
      "specialentry": -1
    },
    "13012": {
      "activityLineId": 13,
      "closeTime": "2022-10-25 03:59:59",
      "id": 13012,
      "onChannel": "",
      "openTime": "2022-10-11 04:00:00",
      "parameter": "",
      "scheduleLimit": 10025,
      "scheduleinterval": 43,
      "specialentry": -1
    },
    "13013": {
      "activityLineId": 13,
      "closeTime": "2022-11-22 03:59:59",
      "id": 13013,
      "onChannel": "",
      "openTime": "2022-11-08 04:00:00",
      "parameter": "",
      "scheduleLimit": 10025,
      "scheduleinterval": 43,
      "specialentry": -1
    },
    "13014": {
      "activityLineId": 13,
      "closeTime": "2022-12-20 03:59:59",
      "id": 13014,
      "onChannel": "",
      "openTime": "2022-12-06 04:00:00",
      "parameter": "",
      "scheduleLimit": 10025,
      "scheduleinterval": 43,
      "specialentry": -1
    },
    "13015": {
      "activityLineId": 13,
      "closeTime": "2023-01-17 03:59:59",
      "id": 13015,
      "onChannel": "",
      "openTime": "2023-01-03 04:00:00",
      "parameter": "",
      "scheduleLimit": 10025,
      "scheduleinterval": 43,
      "specialentry": -1
    },
    "13016": {
      "activityLineId": 13,
      "closeTime": "2023-02-14 03:59:59",
      "id": 13016,
      "onChannel": "",
      "openTime": "2023-01-31 04:00:00",
      "parameter": "",
      "scheduleLimit": 10025,
      "scheduleinterval": 43,
      "specialentry": -1
    },
    "13017": {
      "activityLineId": 13,
      "closeTime": "2023-03-14 03:59:59",
      "id": 13017,
      "onChannel": "",
      "openTime": "2023-02-28 04:00:00",
      "parameter": "",
      "scheduleLimit": 10025,
      "scheduleinterval": 43,
      "specialentry": -1
    },
    "13018": {
      "activityLineId": 13,
      "closeTime": "2023-04-11 03:59:59",
      "id": 13018,
      "onChannel": "",
      "openTime": "2023-03-28 04:00:00",
      "parameter": "",
      "scheduleLimit": 10025,
      "scheduleinterval": 43,
      "specialentry": -1
    },
    "13019": {
      "activityLineId": 13,
      "closeTime": "2023-05-09 03:59:59",
      "id": 13019,
      "onChannel": "",
      "openTime": "2023-04-25 04:00:00",
      "parameter": "",
      "scheduleLimit": 10025,
      "scheduleinterval": 43,
      "specialentry": -1
    },
    "15001": {
      "activityLineId": 15,
      "closeTime": "2021-10-26 03:59:59",
      "id": 15001,
      "onChannel": "",
      "openTime": "2021-09-26 04:00:00",
      "parameter": "",
      "scheduleLimit": 0,
      "scheduleinterval": 0,
      "specialentry": -1
    },
    "15002": {
      "activityLineId": 15,
      "closeTime": "2022-01-06 03:59:59",
      "id": 15002,
      "onChannel": "",
      "openTime": "2021-12-16 04:00:00",
      "parameter": "",
      "scheduleLimit": 0,
      "scheduleinterval": 0,
      "specialentry": -1
    },
    "15004": {
      "activityLineId": 15,
      "closeTime": "2022-03-22 03:59:59",
      "id": 15004,
      "onChannel": "",
      "openTime": "2022-03-08 04:00:00",
      "parameter": "",
      "scheduleLimit": 0,
      "scheduleinterval": 0,
      "specialentry": -1
    },
    "15005": {
      "activityLineId": 15,
      "closeTime": "2022-04-29 03:59:59",
      "id": 15005,
      "onChannel": "",
      "openTime": "2022-04-15 04:00:00",
      "parameter": "",
      "scheduleLimit": 0,
      "scheduleinterval": 0,
      "specialentry": -1
    },
    "15006": {
      "activityLineId": 15,
      "closeTime": "2022-05-24 03:59:59",
      "id": 15006,
      "onChannel": "",
      "openTime": "2022-05-10 04:00:00",
      "parameter": "",
      "scheduleLimit": 0,
      "scheduleinterval": 0,
      "specialentry": -1
    },
    "18001": {
      "activityLineId": 18,
      "closeTime": "2023-01-10 03:59:59",
      "id": 18001,
      "onChannel": "",
      "openTime": "2022-12-20 03:00:00",
      "parameter": "",
      "scheduleLimit": 12025,
      "scheduleinterval": 17,
      "specialentry": -1
    },
    "19001": {
      "activityLineId": 19,
      "closeTime": "2022-10-25 03:59:59",
      "id": 19001,
      "onChannel": "",
      "openTime": "2022-10-18 04:00:00",
      "parameter": "",
      "scheduleLimit": 12004,
      "scheduleinterval": 6,
      "specialentry": -1
    },
    "20001": {
      "activityLineId": 20,
      "closeTime": "2022-08-02 03:59:59",
      "id": 20001,
      "onChannel": "",
      "openTime": "2022-07-19 04:00:00",
      "parameter": "2022-08-01 04:00:00",
      "scheduleLimit": 12004,
      "scheduleinterval": 6,
      "specialentry": -1
    },
    "2001": {
      "activityLineId": 2,
      "closeTime": "2022-01-09 03:59:59",
      "id": 2001,
      "onChannel": "",
      "openTime": "2021-01-14 04:00:00",
      "parameter": "",
      "scheduleLimit": 10010,
      "scheduleinterval": -1,
      "specialentry": -1
    },
    "2002": {
      "activityLineId": 2,
      "closeTime": "2022-03-15 03:59:59",
      "id": 2002,
      "onChannel": "",
      "openTime": "2022-01-18 04:00:00",
      "parameter": "",
      "scheduleLimit": 10010,
      "scheduleinterval": -1,
      "specialentry": -1
    },
    "2003": {
      "activityLineId": 2,
      "closeTime": "2022-05-10 03:59:59",
      "id": 2003,
      "onChannel": "",
      "openTime": "2022-03-15 04:00:00",
      "parameter": "",
      "scheduleLimit": 10010,
      "scheduleinterval": -1,
      "specialentry": -1
    },
    "2004": {
      "activityLineId": 2,
      "closeTime": "2022-07-12 03:59:59",
      "id": 2004,
      "onChannel": "",
      "openTime": "2022-05-17 04:00:00",
      "parameter": "",
      "scheduleLimit": 10010,
      "scheduleinterval": -1,
      "specialentry": -1
    },
    "2005": {
      "activityLineId": 2,
      "closeTime": "2022-09-20 03:59:59",
      "id": 2005,
      "onChannel": "",
      "openTime": "2022-07-19 04:00:00",
      "parameter": "",
      "scheduleLimit": 10010,
      "scheduleinterval": -1,
      "specialentry": -1
    },
    "2006": {
      "activityLineId": 2,
      "closeTime": "2022-11-22 03:59:59",
      "id": 2006,
      "onChannel": "",
      "openTime": "2022-09-20 04:00:00",
      "parameter": "",
      "scheduleLimit": 10010,
      "scheduleinterval": -1,
      "specialentry": -1
    },
    "2007": {
      "activityLineId": 2,
      "closeTime": "2023-01-24 03:59:59",
      "id": 2007,
      "onChannel": "",
      "openTime": "2022-11-22 04:00:00",
      "parameter": "",
      "scheduleLimit": 10010,
      "scheduleinterval": -1,
      "specialentry": -1
    },
    "2008": {
      "activityLineId": 2,
      "closeTime": "2023-03-28 03:59:59",
      "id": 2008,
      "onChannel": "",
      "openTime": "2023-01-31 04:00:00",
      "parameter": "",
      "scheduleLimit": 10010,
      "scheduleinterval": -1,
      "specialentry": -1
    },
    "21001": {
      "activityLineId": 21,
      "closeTime": "2022-08-30 03:59:59",
      "id": 21001,
      "onChannel": "",
      "openTime": "2022-08-16 04:00:00",
      "parameter": "",
      "scheduleLimit": 12025,
      "scheduleinterval": 17,
      "specialentry": -1
    },
    "22001": {
      "activityLineId": 22,
      "closeTime": "2022-08-30 03:59:59",
      "id": 22001,
      "onChannel": "",
      "openTime": "2022-08-16 04:00:00",
      "parameter": "",
      "scheduleLimit": 12025,
      "scheduleinterval": 17,
      "specialentry": -1
    },
    "23001": {
      "activityLineId": 23,
      "closeTime": "2022-09-06 03:59:59",
      "id": 23001,
      "onChannel": "",
      "openTime": "2022-08-30 04:00:00",
      "parameter": "",
      "scheduleLimit": 12025,
      "scheduleinterval": 17,
      "specialentry": -1
    },
    "24001": {
      "activityLineId": 24,
      "closeTime": "2022-09-06 03:59:59",
      "id": 24001,
      "onChannel": "",
      "openTime": "2022-08-16 04:00:00",
      "parameter": "",
      "scheduleLimit": 12025,
      "scheduleinterval": 17,
      "specialentry": -1
    },
    "25001": {
      "activityLineId": 25,
      "closeTime": "2023-02-07 03:59:59",
      "id": 25001,
      "onChannel": "",
      "openTime": "2023-01-17 04:00:00",
      "parameter": "",
      "scheduleLimit": 12004,
      "scheduleinterval": 6,
      "specialentry": -1
    },
    "26001": {
      "activityLineId": 26,
      "closeTime": "2023-01-29 03:59:59",
      "id": 26001,
      "onChannel": "",
      "openTime": "2023-01-22 04:00:00",
      "parameter": "",
      "scheduleLimit": 12004,
      "scheduleinterval": 6,
      "specialentry": -1
    },
    "27001": {
      "activityLineId": 27,
      "closeTime": "2023-03-07 03:59:59",
      "id": 27001,
      "onChannel": "",
      "openTime": "2023-02-14 03:00:00",
      "parameter": "",
      "scheduleLimit": 12025,
      "scheduleinterval": 17,
      "specialentry": -1
    },
    "28001": {
      "activityLineId": 28,
      "closeTime": "2022-02-01 03:59:59",
      "id": 28001,
      "onChannel": "",
      "openTime": "2022-01-18 04:00:00",
      "parameter": "",
      "scheduleLimit": 0,
      "scheduleinterval": -1,
      "specialentry": -1
    },
    "29001": {
      "activityLineId": 29,
      "closeTime": "2023-03-16 03:59:59",
      "id": 29001,
      "onChannel": "",
      "openTime": "2023-03-09 04:00:00",
      "parameter": "",
      "scheduleLimit": 12004,
      "scheduleinterval": 6,
      "specialentry": -1
    },
    "30001": {
      "activityLineId": 30,
      "closeTime": "2023-02-07 03:59:59",
      "id": 30001,
      "onChannel": "",
      "openTime": "2023-01-17 04:00:00",
      "parameter": "",
      "scheduleLimit": 12004,
      "scheduleinterval": 6,
      "specialentry": -1
    },
    "3001": {
      "activityLineId": 3,
      "closeTime": "2122-03-24 10:00:00",
      "id": 3001,
      "onChannel": "",
      "openTime": "2021-03-23 10:00:00",
      "parameter": "",
      "scheduleLimit": 10003,
      "scheduleinterval": -1,
      "specialentry": -1
    },
    "31001": {
      "activityLineId": 31,
      "closeTime": "2022-04-12 03:59:59",
      "id": 31001,
      "onChannel": "",
      "openTime": "2022-03-29 04:00:00",
      "parameter": "",
      "scheduleLimit": 12025,
      "scheduleinterval": 17,
      "specialentry": -1
    },
    "32001": {
      "activityLineId": 32,
      "closeTime": "2022-04-12 03:59:59",
      "id": 32001,
      "onChannel": "",
      "openTime": "2022-03-29 04:00:00",
      "parameter": "",
      "scheduleLimit": 12025,
      "scheduleinterval": 17,
      "specialentry": -1
    },
    "33001": {
      "activityLineId": 33,
      "closeTime": "2022-04-15 03:59:59",
      "id": 33001,
      "onChannel": "",
      "openTime": "2022-03-29 04:00:00",
      "parameter": "",
      "scheduleLimit": 12025,
      "scheduleinterval": 17,
      "specialentry": -1
    },
    "34001": {
      "activityLineId": 34,
      "closeTime": "2022-07-19 03:59:59",
      "id": 34001,
      "onChannel": "",
      "openTime": "2022-01-03 04:00:00",
      "parameter": "2022-07-12 03:59:59",
      "scheduleLimit": 12004,
      "scheduleinterval": 6,
      "specialentry": -1
    },
    "35001": {
      "activityLineId": 35,
      "closeTime": "2022-06-28 03:59:59",
      "id": 35001,
      "onChannel": "",
      "openTime": "2022-06-07 04:00:00",
      "parameter": "",
      "scheduleLimit": 12025,
      "scheduleinterval": 6,
      "specialentry": -1
    },
    "36001": {
      "activityLineId": 36,
      "closeTime": "2022-09-06 03:59:59",
      "id": 36001,
      "onChannel": "",
      "openTime": "2022-08-23 04:00:00",
      "parameter": "",
      "scheduleLimit": 10010,
      "scheduleinterval": -1,
      "specialentry": -1
    },
    "37001": {
      "activityLineId": 37,
      "closeTime": "2022-05-31 03:59:59",
      "id": 37001,
      "onChannel": "",
      "openTime": "2022-05-10 04:00:00",
      "parameter": "",
      "scheduleLimit": 10003,
      "scheduleinterval": -1,
      "specialentry": -1
    },
    "38001": {
      "activityLineId": 38,
      "closeTime": "2024-05-19 03:59:59",
      "id": 38001,
      "onChannel": "",
      "openTime": "2022-06-20 04:00:00",
      "parameter": "",
      "scheduleLimit": 13029,
      "scheduleinterval": 38,
      "specialentry": -1
    },
    "39001": {
      "activityLineId": 39,
      "closeTime": "2022-07-05 03:59:59",
      "id": 39001,
      "onChannel": "",
      "openTime": "2022-06-14 04:00:00",
      "parameter": "",
      "scheduleLimit": 12004,
      "scheduleinterval": 6,
      "specialentry": -1
    },
    "39002": {
      "activityLineId": 39,
      "closeTime": "2022-07-26 03:59:59",
      "id": 39002,
      "onChannel": "",
      "openTime": "2022-07-05 04:00:00",
      "parameter": "",
      "scheduleLimit": 12004,
      "scheduleinterval": 6,
      "specialentry": -1
    },
    "39003": {
      "activityLineId": 39,
      "closeTime": "2022-08-16 03:59:59",
      "id": 39003,
      "onChannel": "",
      "openTime": "2022-07-26 04:00:00",
      "parameter": "",
      "scheduleLimit": 12004,
      "scheduleinterval": 6,
      "specialentry": -1
    },
    "39004": {
      "activityLineId": 39,
      "closeTime": "2022-09-06 03:59:59",
      "id": 39004,
      "onChannel": "",
      "openTime": "2022-08-16 04:00:00",
      "parameter": "",
      "scheduleLimit": 12004,
      "scheduleinterval": 6,
      "specialentry": -1
    },
    "39005": {
      "activityLineId": 39,
      "closeTime": "2022-09-27 03:59:59",
      "id": 39005,
      "onChannel": "",
      "openTime": "2022-09-06 04:00:00",
      "parameter": "",
      "scheduleLimit": 12004,
      "scheduleinterval": 6,
      "specialentry": -1
    },
    "39006": {
      "activityLineId": 39,
      "closeTime": "2022-10-18 03:59:59",
      "id": 39006,
      "onChannel": "",
      "openTime": "2022-09-27 04:00:00",
      "parameter": "",
      "scheduleLimit": 12004,
      "scheduleinterval": 6,
      "specialentry": -1
    },
    "39007": {
      "activityLineId": 39,
      "closeTime": "2022-11-08 03:59:59",
      "id": 39007,
      "onChannel": "",
      "openTime": "2022-10-18 04:00:00",
      "parameter": "",
      "scheduleLimit": 12004,
      "scheduleinterval": 6,
      "specialentry": -1
    },
    "39008": {
      "activityLineId": 39,
      "closeTime": "2022-11-29 03:59:59",
      "id": 39008,
      "onChannel": "",
      "openTime": "2022-11-08 04:00:00",
      "parameter": "",
      "scheduleLimit": 12004,
      "scheduleinterval": 6,
      "specialentry": -1
    },
    "39009": {
      "activityLineId": 39,
      "closeTime": "2022-12-20 03:59:59",
      "id": 39009,
      "onChannel": "",
      "openTime": "2022-11-29 04:00:00",
      "parameter": "",
      "scheduleLimit": 12004,
      "scheduleinterval": 6,
      "specialentry": -1
    },
    "39010": {
      "activityLineId": 39,
      "closeTime": "2023-01-10 03:59:59",
      "id": 39010,
      "onChannel": "",
      "openTime": "2022-12-20 04:00:00",
      "parameter": "",
      "scheduleLimit": 12004,
      "scheduleinterval": 6,
      "specialentry": -1
    },
    "39011": {
      "activityLineId": 39,
      "closeTime": "2023-01-31 03:59:59",
      "id": 39011,
      "onChannel": "",
      "openTime": "2023-01-10 04:00:00",
      "parameter": "",
      "scheduleLimit": 12004,
      "scheduleinterval": 6,
      "specialentry": -1
    },
    "39012": {
      "activityLineId": 39,
      "closeTime": "2023-02-21 03:59:59",
      "id": 39012,
      "onChannel": "",
      "openTime": "2023-01-31 04:00:00",
      "parameter": "",
      "scheduleLimit": 12004,
      "scheduleinterval": 6,
      "specialentry": -1
    },
    "39013": {
      "activityLineId": 39,
      "closeTime": "2023-03-14 03:59:59",
      "id": 39013,
      "onChannel": "",
      "openTime": "2023-02-21 04:00:00",
      "parameter": "",
      "scheduleLimit": 12004,
      "scheduleinterval": 6,
      "specialentry": -1
    },
    "39014": {
      "activityLineId": 39,
      "closeTime": "2023-04-04 03:59:59",
      "id": 39014,
      "onChannel": "",
      "openTime": "2023-03-14 04:00:00",
      "parameter": "",
      "scheduleLimit": 12004,
      "scheduleinterval": 6,
      "specialentry": -1
    },
    "39015": {
      "activityLineId": 39,
      "closeTime": "2023-04-25 03:59:59",
      "id": 39015,
      "onChannel": "",
      "openTime": "2023-04-04 04:00:00",
      "parameter": "",
      "scheduleLimit": 12004,
      "scheduleinterval": 6,
      "specialentry": -1
    },
    "39016": {
      "activityLineId": 39,
      "closeTime": "2023-05-16 03:59:59",
      "id": 39016,
      "onChannel": "",
      "openTime": "2023-04-25 04:00:00",
      "parameter": "",
      "scheduleLimit": 12004,
      "scheduleinterval": 6,
      "specialentry": -1
    },
    "40001": {
      "activityLineId": 40,
      "closeTime": "2022-11-21 03:59:59",
      "id": 40001,
      "onChannel": "",
      "openTime": "2022-10-31 03:00:00",
      "parameter": "",
      "scheduleLimit": 12025,
      "scheduleinterval": 17,
      "specialentry": -1
    },
    "4001": {
      "activityLineId": 4,
      "closeTime": "2021-11-23 03:59:59",
      "id": 4001,
      "onChannel": "",
      "openTime": "2021-11-10 04:00:00",
      "parameter": "",
      "scheduleLimit": 10010,
      "scheduleinterval": -1,
      "specialentry": -1
    },
    "4002": {
      "activityLineId": 4,
      "closeTime": "2021-12-07 03:59:59",
      "id": 4002,
      "onChannel": "",
      "openTime": "2021-11-23 04:00:00",
      "parameter": "",
      "scheduleLimit": 10010,
      "scheduleinterval": -1,
      "specialentry": -1
    },
    "4003": {
      "activityLineId": 4,
      "closeTime": "2021-12-21 03:59:59",
      "id": 4003,
      "onChannel": "",
      "openTime": "2021-12-07 04:00:00",
      "parameter": "",
      "scheduleLimit": 10010,
      "scheduleinterval": -1,
      "specialentry": -1
    },
    "4004": {
      "activityLineId": 4,
      "closeTime": "2022-01-04 03:59:59",
      "id": 4004,
      "onChannel": "",
      "openTime": "2021-12-21 04:00:00",
      "parameter": "",
      "scheduleLimit": 10010,
      "scheduleinterval": -1,
      "specialentry": -1
    },
    "4005": {
      "activityLineId": 4,
      "closeTime": "2022-01-18 03:59:59",
      "id": 4005,
      "onChannel": "",
      "openTime": "2022-01-04 04:00:00",
      "parameter": "",
      "scheduleLimit": 10010,
      "scheduleinterval": -1,
      "specialentry": -1
    },
    "4006": {
      "activityLineId": 4,
      "closeTime": "2022-02-01 03:59:59",
      "id": 4006,
      "onChannel": "",
      "openTime": "2022-01-18 04:00:00",
      "parameter": "",
      "scheduleLimit": 10010,
      "scheduleinterval": -1,
      "specialentry": -1
    },
    "4007": {
      "activityLineId": 4,
      "closeTime": "2022-02-15 03:59:59",
      "id": 4007,
      "onChannel": "",
      "openTime": "2022-02-01 04:00:00",
      "parameter": "",
      "scheduleLimit": 10010,
      "scheduleinterval": -1,
      "specialentry": -1
    },
    "4008": {
      "activityLineId": 4,
      "closeTime": "2022-03-01 03:59:59",
      "id": 4008,
      "onChannel": "",
      "openTime": "2022-02-15 04:00:00",
      "parameter": "",
      "scheduleLimit": 10010,
      "scheduleinterval": -1,
      "specialentry": -1
    },
    "4009": {
      "activityLineId": 4,
      "closeTime": "2022-03-15 03:59:59",
      "id": 4009,
      "onChannel": "",
      "openTime": "2022-03-01 04:00:00",
      "parameter": "",
      "scheduleLimit": 10010,
      "scheduleinterval": -1,
      "specialentry": -1
    },
    "4010": {
      "activityLineId": 4,
      "closeTime": "2022-03-29 03:59:59",
      "id": 4010,
      "onChannel": "",
      "openTime": "2022-03-15 04:00:00",
      "parameter": "",
      "scheduleLimit": 10010,
      "scheduleinterval": -1,
      "specialentry": -1
    },
    "4011": {
      "activityLineId": 4,
      "closeTime": "2022-04-12 03:59:59",
      "id": 4011,
      "onChannel": "",
      "openTime": "2022-03-29 04:00:00",
      "parameter": "",
      "scheduleLimit": 10010,
      "scheduleinterval": -1,
      "specialentry": -1
    },
    "4012": {
      "activityLineId": 4,
      "closeTime": "2022-04-26 03:59:59",
      "id": 4012,
      "onChannel": "",
      "openTime": "2022-04-12 04:00:00",
      "parameter": "",
      "scheduleLimit": 10010,
      "scheduleinterval": -1,
      "specialentry": -1
    },
    "41001": {
      "activityLineId": 41,
      "closeTime": "2035-07-19 03:59:59",
      "id": 41001,
      "onChannel": "",
      "openTime": "2022-05-01 04:00:00",
      "parameter": "",
      "scheduleLimit": 10011,
      "scheduleinterval": 4,
      "specialentry": -1
    },
    "42001": {
      "activityLineId": 42,
      "closeTime": "2022-08-16 03:59:59",
      "id": 42001,
      "onChannel": "",
      "openTime": "2022-08-02 04:00:00",
      "parameter": "",
      "scheduleLimit": 12025,
      "scheduleinterval": 17,
      "specialentry": -1
    },
    "42002": {
      "activityLineId": 42,
      "closeTime": "2022-11-14 03:59:59",
      "id": 42002,
      "onChannel": "",
      "openTime": "2022-10-20 15:00:00",
      "parameter": "",
      "scheduleLimit": 12025,
      "scheduleinterval": 17,
      "specialentry": -1
    },
    "43001": {
      "activityLineId": 43,
      "closeTime": "2022-07-08 03:59:59",
      "id": 43001,
      "onChannel": "",
      "openTime": "2022-06-06 04:00:00",
      "parameter": "",
      "scheduleLimit": 12025,
      "scheduleinterval": 17,
      "specialentry": -1
    },
    "44001": {
      "activityLineId": 44,
      "closeTime": "2022-11-14 03:59:59",
      "id": 44001,
      "onChannel": "",
      "openTime": "2022-10-31 03:00:00",
      "parameter": "",
      "scheduleLimit": 12025,
      "scheduleinterval": 17,
      "specialentry": -1
    },
    "45001": {
      "activityLineId": 45,
      "closeTime": "2022-08-04 03:59:59",
      "id": 45001,
      "onChannel": "",
      "openTime": "2021-06-19 04:00:00",
      "parameter": "",
      "scheduleLimit": 12004,
      "scheduleinterval": 6,
      "specialentry": -1
    },
    "45002": {
      "activityLineId": 45,
      "closeTime": "2022-12-06 03:59:59",
      "id": 45002,
      "onChannel": "",
      "openTime": "2022-11-22 03:00:00",
      "parameter": "",
      "scheduleLimit": 12004,
      "scheduleinterval": 6,
      "specialentry": -1
    },
    "46001": {
      "activityLineId": 46,
      "closeTime": "2022-10-18 03:59:59",
      "id": 46001,
      "onChannel": "",
      "openTime": "2022-09-27 03:00:00",
      "parameter": "2022-10-11 04:00:00",
      "scheduleLimit": 12025,
      "scheduleinterval": 17,
      "specialentry": -1
    },
    "47001": {
      "activityLineId": 47,
      "closeTime": "2022-10-04 03:59:59",
      "id": 47001,
      "onChannel": "",
      "openTime": "2022-09-13 04:00:00",
      "parameter": "",
      "scheduleLimit": 12025,
      "scheduleinterval": 17,
      "specialentry": -1
    },
    "48001": {
      "activityLineId": 48,
      "closeTime": "2022-09-13 03:59:59",
      "id": 48001,
      "onChannel": "",
      "openTime": "2022-08-30 04:00:00",
      "parameter": "",
      "scheduleLimit": 10003,
      "scheduleinterval": -1,
      "specialentry": -1
    },
    "5001": {
      "activityLineId": 5,
      "closeTime": "2021-02-01 12:00:00",
      "id": 5001,
      "onChannel": "110001;610001;610002",
      "openTime": "2020-12-04 12:00:00",
      "parameter": "35001;1",
      "scheduleLimit": 10003,
      "scheduleinterval": -1,
      "specialentry": -1
    },
    "6001": {
      "activityLineId": 6,
      "closeTime": "2021-12-14 04:00:00",
      "id": 6001,
      "onChannel": "",
      "openTime": "2021-11-23 13:00:00",
      "parameter": "",
      "scheduleLimit": 12025,
      "scheduleinterval": 17,
      "specialentry": -1
    },
    "7001": {
      "activityLineId": 7,
      "closeTime": "2022-01-25 03:59:59",
      "id": 7001,
      "onChannel": "",
      "openTime": "2022-01-11 04:00:00",
      "parameter": "",
      "scheduleLimit": 10003,
      "scheduleinterval": -1,
      "specialentry": -1
    },
    "7003": {
      "activityLineId": 7,
      "closeTime": "2021-12-30 03:59:59",
      "id": 7003,
      "onChannel": "",
      "openTime": "2021-12-16 04:00:00",
      "parameter": "",
      "scheduleLimit": 10003,
      "scheduleinterval": -1,
      "specialentry": -1
    },
    "7004": {
      "activityLineId": 7,
      "closeTime": "2022-02-15 03:59:59",
      "id": 7004,
      "onChannel": "",
      "openTime": "2022-01-25 04:00:00",
      "parameter": "",
      "scheduleLimit": 10003,
      "scheduleinterval": 3,
      "specialentry": -1
    },
    "7005": {
      "activityLineId": 7,
      "closeTime": "2022-01-25 03:59:59",
      "id": 7005,
      "onChannel": "",
      "openTime": "2021-12-31 04:00:00",
      "parameter": "",
      "scheduleLimit": 10003,
      "scheduleinterval": 3,
      "specialentry": -1
    },
    "7006": {
      "activityLineId": 7,
      "closeTime": "2031-01-14 03:59:59",
      "id": 7006,
      "onChannel": "",
      "openTime": "2021-12-31 04:00:00",
      "parameter": "",
      "scheduleLimit": 10003,
      "scheduleinterval": 3,
      "specialentry": -1
    },
    "7008": {
      "activityLineId": 7,
      "closeTime": "2022-04-29 03:59:59",
      "id": 7008,
      "onChannel": "",
      "openTime": "2022-04-15 04:00:00",
      "parameter": "",
      "scheduleLimit": 12025,
      "scheduleinterval": 17,
      "specialentry": -1
    },
    "7009": {
      "activityLineId": 7,
      "closeTime": "2022-05-31 03:59:59",
      "id": 7009,
      "onChannel": "",
      "openTime": "2022-05-10 04:00:00",
      "parameter": "",
      "scheduleLimit": 12025,
      "scheduleinterval": 17,
      "specialentry": -1
    },
    "7010": {
      "activityLineId": 7,
      "closeTime": "2022-08-23 03:59:59",
      "id": 7010,
      "onChannel": "",
      "openTime": "2022-08-02 04:00:00",
      "parameter": "",
      "scheduleLimit": 10003,
      "scheduleinterval": -1,
      "specialentry": -1
    },
    "7012": {
      "activityLineId": 7,
      "closeTime": "2022-10-11 03:59:59",
      "id": 7012,
      "onChannel": "",
      "openTime": "2022-09-27 03:00:00",
      "parameter": "",
      "scheduleLimit": 10003,
      "scheduleinterval": -1,
      "specialentry": -1
    },
    "7013": {
      "activityLineId": 7,
      "closeTime": "2022-11-21 03:59:59",
      "id": 7013,
      "onChannel": "",
      "openTime": "2022-10-27 04:00:00",
      "parameter": "",
      "scheduleLimit": 10003,
      "scheduleinterval": -1,
      "specialentry": -1
    },
    "7014": {
      "activityLineId": 7,
      "closeTime": "2022-11-24 03:59:59",
      "id": 7014,
      "onChannel": "",
      "openTime": "2022-11-08 04:00:00",
      "parameter": "",
      "scheduleLimit": 10003,
      "scheduleinterval": -1,
      "specialentry": -1
    },
    "7015": {
      "activityLineId": 7,
      "closeTime": "2023-02-07 03:59:59",
      "id": 7015,
      "onChannel": "",
      "openTime": "2023-01-17 04:00:00",
      "parameter": "",
      "scheduleLimit": 10010,
      "scheduleinterval": 3,
      "specialentry": -1
    },
    "7016": {
      "activityLineId": 7,
      "closeTime": "2023-04-25 03:59:59",
      "id": 7016,
      "onChannel": "",
      "openTime": "2023-04-11 03:00:00",
      "parameter": "",
      "scheduleLimit": 10003,
      "scheduleinterval": -1,
      "specialentry": -1
    },
    "8004": {
      "activityLineId": 8,
      "closeTime": "2082-07-14 03:59:59",
      "id": 8004,
      "onChannel": "",
      "openTime": "2022-08-30 04:00:00",
      "parameter": "",
      "scheduleLimit": 10003,
      "scheduleinterval": -1,
      "specialentry": -1
    },
    "801003": {
      "activityLineId": 801,
      "closeTime": "2082-07-14 03:59:59",
      "id": 801003,
      "onChannel": "",
      "openTime": "2022-08-30 04:00:00",
      "parameter": "",
      "scheduleLimit": 10003,
      "scheduleinterval": -1,
      "specialentry": -1
    },
    "802003": {
      "activityLineId": 802,
      "closeTime": "2022-09-13 03:59:59",
      "id": 802003,
      "onChannel": "",
      "openTime": "2022-08-30 04:00:00",
      "parameter": "",
      "scheduleLimit": 10003,
      "scheduleinterval": -1,
      "specialentry": -1
    },
    "802004": {
      "activityLineId": 802,
      "closeTime": "2022-11-22 03:59:59",
      "id": 802004,
      "onChannel": "",
      "openTime": "2022-11-08 04:00:00",
      "parameter": "",
      "scheduleLimit": 10003,
      "scheduleinterval": -1,
      "specialentry": -1
    },
    "803003": {
      "activityLineId": 803,
      "closeTime": "2082-07-14 03:59:59",
      "id": 803003,
      "onChannel": "",
      "openTime": "2022-08-30 04:00:00",
      "parameter": "",
      "scheduleLimit": 10003,
      "scheduleinterval": -1,
      "specialentry": -1
    },
    "804003": {
      "activityLineId": 804,
      "closeTime": "2022-10-04 03:59:59",
      "id": 804003,
      "onChannel": "",
      "openTime": "2022-08-30 04:00:00",
      "parameter": "",
      "scheduleLimit": 10003,
      "scheduleinterval": -1,
      "specialentry": -1
    },
    "804004": {
      "activityLineId": 804,
      "closeTime": "2022-12-13 03:59:59",
      "id": 804004,
      "onChannel": "",
      "openTime": "2022-11-08 04:00:00",
      "parameter": "",
      "scheduleLimit": 10003,
      "scheduleinterval": -1,
      "specialentry": -1
    },
    "9001": {
      "activityLineId": 9,
      "closeTime": "2022-05-31 03:59:59",
      "id": 9001,
      "onChannel": "",
      "openTime": "2022-05-10 04:00:00",
      "parameter": "",
      "scheduleLimit": 12025,
      "scheduleinterval": 17,
      "specialentry": -1
    }
  }
}
